Workbook

Sheet ЗАКАЗЫ
A1: ID | B1: Дата | C1: Время | D1: Столик | E1: Гости | F1: Официант | G1: Блюда | H1: Сумма (₸) | I1: Оплата | J1: Примечание | K1: Статус | L1: Создано
A2: 8129E1F5FE | B2: 10.06.2026 | C2: 10:30 | D2: 3 | E2: 2 | F2: Анна | G2: Капучино, Чизкейк | H2: 650 | I2: Карта | K2: Новый
A3: F5343C88FC | B3: 10.06.2026 | C3: 13:15 | D3: 5 | E3: 4 | F3: Иван | G3: 2x Пицца, 3x Чай | H3: 2450 | I3: Наличные | K3: Новый
A4: 4E0AC2F454 | B4: 10.06.2026 | C4: 14:00 | D4: 1 | E4: 1 | F4: Анна | G4: Суп, Хлеб | H4: 380 | I4: Карта | K4: Новый
A5: 42490AA9EE | B5: 10.06.2026 | C5: 17:30 | D5: 2 | E5: 2 | F5: Иван | G5: Латте, Круассан | H5: 520 | I5: Карта | K5: Новый
A6: 9F83592152 | B6: 10.06.2026 | C6: 18:45 | D6: 4 | E6: 3 | F6: Анна | G6: 2x Пицца, 2x Чай | H6: 2450 | I6: Наличные | K6: Новый
A7: 3D2EABE1E1 | B7: ИТОГО за день: | K7: Новый
A8: 41FCC8E177 | B8: Средний чек: | K8: Новый
A9: 96D97467EA | B9: 10.06.2026 | C9: 11:57 | D9: 1 | E9: 2 | F9: Анна | G9: Чизкейк | H9: 350 | I9: Наличные | K9: Новый
A10: B02D2D3CD3 | B10: 10.06.2026 | C10: 12:35 | D10: 10 | E10: 5 | F10: Иван | G10: Хлеб, Латте, Чизкейк, Капучино | H10: 1000 | I10: Наличные | K10: Новый
A11: EBFB463131 | B11: 17.06.2026 | C11: 12:44 | D11: 1 | E11: 2 | F11: Сергей | G11: Капучино, Пицца Маргарита, Суп куриный, Хлеб, Чизкейк, Латте, Круассан, Чай | H11: 2130 | I11: Наличные | K11: Новый
A12: D277BC34ED | B12: 10.06.2026 | C12: 13:15 | D12: 1 | E12: 2 | F12: Анна | G12: Капучино, Чизкейк, Пицца Маргарита | H12: 1150 | I12: Наличные | K12: Новый
A13: B3F211F794 | B13: 10.06.2026 | C13: 16:24 | D13: 1 | E13: 2 | F13: Мярт | G13: Латте, Капучино, Суп куриный | H13: 830 | I13: Наличные | K13: Новый

Sheet МЕНЮ
A1: Блюдо | B1: Категория | C1: Ингредиенты | D1: Себестоимость (₸) | E1: Цена продажи (₸) | F1: Маржинальность (%)
A2: Капучино | B2: Напитки | C2: Кофе, молоко | D2: 0 | E2: 0 | F2: 0
A3: Чизкейк | B3: Десерты | C3: Сыр, печенье | D3: 0 | E3: 0 | F3: 0
A4: Суп куриный | B4: Первые блюда | C4: Курица, овощи | D4: 0 | E4: 0 | F4: 0
A5: Латте | B5: Напитки | C5: Кофе, молоко | D5: 0 | E5: 0 | F5: 0
A6: Круассан | B6: Выпечка | C6: Мука, масло | D6: 0 | E6: 0 | F6: 0
A7: Американо | B7: Напитки | D7: 0 | E7: 0 | F7: 0
A8: Эспрессо | B8: Напитки | D8: 0 | E8: 0 | F8: 0
A9: Чай холодный | B9: Напитки | D9: 0 | E9: 0 | F9: 0
A10: Лимонад | B10: Напитки | D10: 0 | E10: 0 | F10: 0
A11: Морс | B11: Напитки | D11: 0 | E11: 0 | F11: 0
A12: Апельсиновый | B12: Напитки | D12: 0 | E12: 0 | F12: 0
A13: Яблочный | B13: Напитки | D13: 0 | E13: 0 | F13: 0
A14: Мультифрукт | B14: Напитки | D14: 0 | E14: 0 | F14: 0
A15: Куриный шашлык | B15: Шашлыки | D15: 0 | E15: 0 | F15: 0
A16: Крылышки гриль | B16: Шашлыки | D16: 0 | E16: 0 | F16: 0
A17: Говяжий шашлык | B17: Шашлыки | D17: 0 | E17: 0 | F17: 0
A18: Люля-кебаб | B18: Шашлыки | D18: 0 | E18: 0 | F18: 0
... A52: Шоколадное | B52: Десерты | D52: 0 | E52: 0 | F52: 0

Sheet ИНГРЕДИЕНТЫ
A1: Ингредиент | B1: Единица | C1: Остаток | D1: Мин. запас | E1: Цена за ед. (₸) | F1: Нужно заказать?
A2: Кофе | B2: г | C2: 5000 | D2: 1000 | E2: 0.5
A3: Молоко | B3: л | C3: 20 | D3: 5 | E3: 300
A4: Мука | B4: кг | C4: 15 | D4: 3 | E4: 150
A5: Сыр | B5: кг | C5: 8 | D5: 2 | E5: 800
A6: Курица | B6: кг | C6: 10 | D6: 2 | E6: 600
A7: Овощи | B7: кг | C7: 12 | D7: 3 | E7: 200
A8: Печенье | B8: кг | C8: 5 | D8: 1 | E8: 400
A9: Масло | B9: кг | C9: 4 | D9: 1 | E9: 350
A10: Дрожжи | B10: г | C10: 1000 | D10: 200 | E10: 0.3
A11: Соус | B11: л | C11: 10 | D11: 2 | E11: 250
A12: Чай | B12: г | C12: 3000 | D12: 500 | E12: 0.2
A13: Сахар | B13: кг | C13: 8 | D13: 2 | E13: 120
A14: изюм | B14: кг | C14: 10 | D14: 2 | E14: 100

Sheet РЕЦЕПТЫ
A1: Блюдо | B1: Ингредиент | C1: Кол-во на порцию | D1: Единица
A2: Капучино | B2: Кофе | C2: 10 | D2: г
A3: Капучино | B3: Молоко | C3: 0.15 | D3: л
A4: Капучино | B4: Сахар | C4: 5 | D4: г
A5: Латте | B5: Кофе | C5: 10 | D5: г
A6: Латте | B6: Молоко | C6: 0.2 | D6: л
A7: Чай | B7: Чай | C7: 2 | D7: г
A8: Чай | B8: Сахар | C8: 5 | D8: г
A9: Пицца Маргарита | B9: Мука | C9: 0.2 | D9: кг
A10: Пицца Маргарита | B10: Соус | C10: 0.05 | D10: л
A11: Пицца Маргарита | B11: Сыр | C11: 0.1 | D11: кг
A12: Суп куриный | B12: Курица | C12: 0.15 | D12: кг
A13: Суп куриный | B13: Овощи | C13: 0.2 | D13: кг
... A19: Чизкейк | B19: Сыр | C19: 0.08 | D19: кг

Sheet ФУДКОСТ
A1: Показатель | B1: Сегодня | C1: Неделя | D1: Месяц
A2: Выручка (₸) | B2: =ЗАКАЗЫ!G8 -> 0 | C2: =SUM(ЗАКАЗЫ!G:G)/4*7 -> 0 | D2: =SUM(ЗАКАЗЫ!G:G) -> 0
A3: Себестоимость (₸) | B3: =SUMPRODUCT(ЗАКАЗЫ!G2:G100, МЕНЮ!C2:C100/МЕНЮ!D2:D100) -> #VALUE!
A4: Фудкост (%) | B4: =B3/B2*100 -> #VALUE! | C4: =C3/C2*100 -> #DIV/0! | D4: =D3/D2*100 -> #DIV/0!

Sheet P&L
A1: Показатель | B1: Сумма (₸) | C1: % от выручки
A2: Выручка | B2: =ФУДКОСТ!B2 -> 0 | C2: 100%
A3: Себестоимость продуктов | B3: =ФУДКОСТ!B3 -> #VALUE! | C3: =B3/B2*100 -> #VALUE!
A4: Валовая прибыль | B4: =B2-B3 -> #VALUE! | C4: =B4/B2*100 -> #VALUE!
A6: Расходы:
A7: Зарплата персонала | B7: 250000 | C7: =B6/B2*100 -> #DIV/0!
A8: Аренда | B8: 150000 | C8: =B7/B2*100 -> #DIV/0!
A9: Коммунальные услуги | B9: 50000 | C9: =B8/B2*100 -> #DIV/0!
A10: Прочие расходы | B10: 80000 | C10: =B9/B2*100 -> #DIV/0!
A11: Итого расходов | B11: =SUM(B6:B9) -> 450000 | C11: =B10/B2*100 -> #DIV/0!
A13: Чистая прибыль | B13: =B2-B3-B10 -> #VALUE! | C13: =B12/B2*100 -> #DIV/0!

Sheet ABC_АНАЛИЗ
A1: Блюдо | B1: Кол-во продаж | C1: Выручка (₸) | D1: Доля в выручке | E1: Категория
A2: Пицца | B2: 50 | C2: 27500 | D2: =C2/SUM(C:C)*100 -> 23.440164 | E2: =IF(D2>=40,"A",IF(D2>=15,"B","C")) -> B
A3: Капучино | B3: 40 | C3: 10000 | D3: =C3/SUM(C:C)*100 -> 8.5236959 | E3: =IF(D3>=40,"A",IF(D3>=15,"B","C")) -> C
A4: Чай | B4: 35 | C4: 3500 | D4: =C4/SUM(C:C)*100 -> 2.9832936 | E4: =IF(D4>=40,"A",IF(D4>=15,"B","C")) -> C
A5: Чизкейк | B5: 20 | C5: 7000 | D5: =C5/SUM(C:C)*100 -> 5.9665871 | E5: =IF(D5>=40,"A",IF(D5>=15,"B","C")) -> C
A6: Латте | B6: 15 | C6: 4500 | D6: =C6/SUM(C:C)*100 -> 3.8356631 | E6: =IF(D6>=40,"A",IF(D6>=15,"B","C")) -> C
A7: Суп | B7: 12 | C7: 3360 | D7: =C7/SUM(C:C)*100 -> 2.8639618 | E7: =IF(D7>=40,"A",IF(D7>=15,"B","C")) -> C
A8: Круассан | B8: 10 | C8: 2000 | D8: =C8/SUM(C:C)*100 -> 1.7047392 | E8: =IF(D8>=40,"A",IF(D8>=15,"B","C")) -> C
A9: Хлеб | B9: 8 | C9: 800 | D9: =C9/SUM(C:C)*100 -> 0.68189567 | E9: =IF(D9>=40,"A",IF(D9>=15,"B","C")) -> C
A10: ИТОГО: | C10: =SUM(C2:C9) -> 58660

Sheet КАТЕГОРИИ
A1: Категория
A2: Вторые блюда
A3: Выпечка
A4: Десерты
A5: Донер
A6: Напитки
A7: Первые блюда
A8: Пицца
A9: Соусы
A10: Фастфуд
A11: Шашлыки

Sheet ПОДКАТЕГОРИИ
A1: Основная категория | B1: Подкатегория | C1: Блюдо
A2: Напитки | B2: Горячие напитки | C2: Капучино
A3: Напитки | B3: Горячие напитки | C3: Латте
A4: Напитки | B4: Горячие напитки | C4: Американо
A5: Напитки | B5: Горячие напитки | C5: Эспрессо
A6: Напитки | B6: Холодные напитки | C6: Чай холодный
A7: Напитки | B7: Холодные напитки | C7: Лимонад
A8: Напитки | B8: Холодные напитки | C8: Морс
A9: Напитки | B9: Соки | C9: Апельсиновый
A10: Напитки | B10: Соки | C10: Яблочный
A11: Напитки | B11: Соки | C11: Мультифрукт
A12: Шашлыки | B12: Шашлык из курицы | C12: Куриный шашлык
... A52: Десерты | B52: Мороженое | C52: Шоколадное

Sheet КАТЕГОРИИ_ПОЛНАЯ
A1: Основная категория | B1: Подкатегория | C1: Блюдо | D1: Цена (₸) | E1: Себестоимость (₸)
A2: Напитки | B2: Горячие напитки | C2: Капучино | D2: 0 | E2: 0
A3: Напитки | B3: Горячие напитки | C3: Латте | D3: 0 | E3: 0
A4: Напитки | B4: Горячие напитки | C4: Американо | D4: 0 | E4: 0
A5: Напитки | B5: Горячие напитки | C5: Эспрессо | D5: 0 | E5: 0
A6: Напитки | B6: Холодные напитки | C6: Чай холодный | D6: 0 | E6: 0
A7: Напитки | B7: Холодные напитки | C7: Лимонад | D7: 0 | E7: 0
A8: Напитки | B8: Холодные напитки | C8: Морс | D8: 0 | E8: 0
A9: Напитки | B9: Соки | C9: Апельсиновый | D9: 0 | E9: 0
A10: Напитки | B10: Соки | C10: Яблочный | D10: 0 | E10: 0
A11: Напитки | B11: Соки | C11: Мультифрукт | D11: 0 | E11: 0
A12: Шашлыки | B12: Шашлык из курицы | C12: Куриный шашлык | D12: 0 | E12: 0
A13: Шашлыки | B13: Шашлык из курицы | C13: Крылышки гриль | D13: 0 | E13: 0
... A52: Десерты | B52: Мороженое | C52: Шоколадное | D52: 0 | E52: 0

Sheet ПЕРСОНАЛ
A1: ID | B1: Имя | C1: Должность | D1: Телефон | E1: PIN-код | F1: Активен | G1: Дата добавления
A2: 3 | B2: Сергей | C2: Администратор | D2: +7XXX | E2: 0 | F2: Да | G2: 10.06.2026
A3: 4 | B3: Мярт | C3: Официант | E3: 7777 | F3: Да | G3: 10.06.2026
A4: 5 | B4: Admin | C4: Администратор | E4: 1988 | F4: Да | G4: 12.06.2026
A5: 6 | B5: Admin | C5: Администратор | E5: 1988 | F5: Да | G5: 12.06.2026
